<?xml version="1.0" encoding="utf-8" ?>
<dwsync>
<file name="contact.php" server="linux.gl.umbc.edu//afs/umbc.edu/public/virthost/domains/techm.umbc.edu/" local="131332999656738466" remote="131340799540000000" Dst="2" />
<file name="costs.php" server="linux.gl.umbc.edu//afs/umbc.edu/public/virthost/domains/techm.umbc.edu/" local="131237833160000000" remote="131340799540000000" Dst="2" />
<file name="courses.php" server="linux.gl.umbc.edu//afs/umbc.edu/public/virthost/domains/techm.umbc.edu/" local="131340598140000000" remote="131340799540000000" Dst="2" />
<file name="directions.php" server="linux.gl.umbc.edu//afs/umbc.edu/public/virthost/domains/techm.umbc.edu/" local="131237833430000000" remote="131340799540000000" Dst="2" />
<file name="faculty.php" server="linux.gl.umbc.edu//afs/umbc.edu/public/virthost/domains/techm.umbc.edu/" local="131332996656088431" remote="131340799550000000" Dst="2" />
<file name="index.php" server="linux.gl.umbc.edu//afs/umbc.edu/public/virthost/domains/techm.umbc.edu/" local="131340592950000000" remote="131340799580000000" Dst="2" />
<file name="international.php" server="linux.gl.umbc.edu//afs/umbc.edu/public/virthost/domains/techm.umbc.edu/" local="131340609390000000" remote="131340799580000000" Dst="2" />
<file name="masters.php" server="linux.gl.umbc.edu//afs/umbc.edu/public/virthost/domains/techm.umbc.edu/" local="131340605820000000" remote="131340799590000000" Dst="2" />
<file name="programmaster.php" server="linux.gl.umbc.edu//afs/umbc.edu/public/virthost/domains/techm.umbc.edu/" local="131340650848599962" remote="131340799590000000" Dst="2" />
<file name="schedule.php" server="linux.gl.umbc.edu//afs/umbc.edu/public/virthost/domains/techm.umbc.edu/" local="131340603250000000" remote="131340799590000000" Dst="2" />
<file name="studentforms.php" server="linux.gl.umbc.edu//afs/umbc.edu/public/virthost/domains/techm.umbc.edu/" local="131330312340000000" remote="131340799590000000" Dst="2" />
<file name="studentresources.php" server="linux.gl.umbc.edu//afs/umbc.edu/public/virthost/domains/techm.umbc.edu/" local="131237834650000000" remote="131340799590000000" Dst="2" />
<file name="tuitionremission.php" server="linux.gl.umbc.edu//afs/umbc.edu/public/virthost/domains/techm.umbc.edu/" local="131340616380000000" remote="131340799590000000" Dst="2" />
</dwsync>